{
    "switches": 1,
    "max time": 9999999,
    "default input gap": 10000,
    "random seed": 0,
    "events": [ 
      {"name":"ip_pkt", "args": [600,3,2]},
      {"name":"ip_pkt", "args": [600,3,2]},
      {"name":"ip_pkt", "args": [600,3,2]},
      {"name":"ip_pkt", "args": [600,3,2]},
      {"name":"ip_pkt", "args": [0,1,2]},
      {"name":"ip_pkt", "args": [0,1,2]},
      {"name":"ip_pkt", "args": [0,1,2]},
      {"name":"ip_pkt", "args": [0,1,2]}, 
      {"name":"ip_pkt", "args": [0,2,2]},
      {"name":"ip_pkt", "args": [6000,2,2]},
      {"name":"ip_pkt", "args": [0,2,2]},
      {"name":"ip_pkt", "args": [600,2,2]}
      
    ]
  }