{"PortToVeth": [{"device_port":128, "veth1":256, "veth2":257},{"device_port":129, "veth1":258, "veth2":259},{"device_port":130, "veth1":260, "veth2":261},{"device_port":131, "veth1":262, "veth2":263},{"device_port":132, "veth1":264, "veth2":265},{"device_port":136, "veth1":272, "veth2":273},{"device_port":140, "veth1":280, "veth2":281},{"device_port":144, "veth1":288, "veth2":289},{"device_port":148, "veth1":296, "veth2":297},{"device_port":152, "veth1":304, "veth2":305},{"device_port":156, "veth1":312, "veth2":313},{"device_port":160, "veth1":320, "veth2":321},{"device_port":164, "veth1":328, "veth2":329},{"device_port":168, "veth1":336, "veth2":337},{"device_port":172, "veth1":344, "veth2":345},{"device_port":176, "veth1":352, "veth2":353},{"device_port":180, "veth1":360, "veth2":361},{"device_port":184, "veth1":368, "veth2":369},{"device_port":188, "veth1":376, "veth2":377},{"device_port":192, "veth1":384, "veth2":385},{"device_port":196, "veth1":392, "veth2":393}]}
